stratilib/__init__.py
stratilib/defaults.py
stratilib/functions.py
stratilib/lithology.py
stratilib/sedlogdef.py
stratilib/sedlogfunc.py
stratilib/images/cl.png
stratilib/images/cr.png
stratilib/images/fal.png
stratilib/images/fbi.png
stratilib/images/fbioh.png
stratilib/images/fbiol.png
stratilib/images/fbiom.png
stratilib/images/fbr.png
stratilib/images/fbry.png
stratilib/images/fcco.png
stratilib/images/fce.png
stratilib/images/fcr.png
stratilib/images/fec.png
stratilib/images/ffo.png
stratilib/images/fga.png
stratilib/images/fhbu.png
stratilib/images/flm.png
stratilib/images/flo.png
stratilib/images/fos.png
stratilib/images/fplm.png
stratilib/images/fra.png
stratilib/images/fro.png
stratilib/images/fsco.png
stratilib/images/fsh.png
stratilib/images/fsp.png
stratilib/images/fst.png
stratilib/images/ftra.png
stratilib/images/ftrk.png
stratilib/images/ftrs.png
stratilib/images/fvbu.png
stratilib/images/fve.png
stratilib/images/gro.png
stratilib/images/h.png
stratilib/images/hb.png
stratilib/images/hm.png
stratilib/images/int.png
stratilib/images/lc.png
stratilib/images/mc.png
stratilib/images/mcl.png
stratilib/images/nac.png
stratilib/images/p.png
stratilib/images/ripple.png
stratilib/images/sc.png
stratilib/images/scr.png
stratilib/images/sw.png
stratilib/images/wripple.png
stratilib/images/ws.png
stratilib-0.1.0.dist-info/LICENCE
stratilib-0.1.0.dist-info/METADATA
stratilib-0.1.0.dist-info/WHEEL
stratilib-0.1.0.dist-info/top_level.txt
stratilib-0.1.0.dist-info/RECORD
