Metadata-Version: 2.1
Name: stratilib
Version: 0.1.0
Summary: Librería para ploteo de columnas estratigráficas
Home-page: https://github.com/rubensdmp/stratilib
Author: Rubens Merlino
Author-email: rubensdmp@gmail.com
License: GNU GPLv3
Platform: UNKNOWN
Requires-Dist: numpy
Requires-Dist: pandas
Requires-Dist: matplotlib
